langdist/__init__.py
langdist/_version.py
langdist/batch.py
langdist/cli.py
langdist/constant.py
langdist/encoder.py
langdist/langmodel.py
langdist/preprocess.py
langdist/transliterator.py
langdist/util.py
langdist-0.4.1.dist-info/DESCRIPTION.rst
langdist-0.4.1.dist-info/METADATA
langdist-0.4.1.dist-info/RECORD
langdist-0.4.1.dist-info/WHEEL
langdist-0.4.1.dist-info/entry_points.txt
langdist-0.4.1.dist-info/metadata.json
langdist-0.4.1.dist-info/top_level.txt
