Metadata-Version: 2.0
Name: langdist
Version: 0.4.1
Summary: Multilingual Language Modeling Toolkit
Home-page: https://github.com/kensk8er/langdist
Author: Kensuke Muraki
Author-email: kensk8er1017@gmail.com
License: UNKNOWN
Keywords: language-model natural-language-processing natural-language-generation machine-learning tensorflow deep-learning recurrent-neural-networks lstm multilingual nlp python neural-network character-embeddings data-science
Platform: UNKNOWN
Classifier: Development Status :: 3 - Alpha
Classifier: Programming Language :: Python
Classifier: Programming Language :: Python :: 3
Classifier: Programming Language :: Python :: 3.5
Classifier: Intended Audience :: Science/Research
Classifier: License :: OSI Approved :: MIT License
Classifier: Operating System :: OS Independent
Classifier: Topic :: Scientific/Engineering :: Artificial Intelligence
Classifier: Topic :: Text Processing :: Linguistic
Classifier: Topic :: Software Development :: Libraries :: Python Modules
Requires-Dist: docopt (>=0.6.2)
Requires-Dist: jieba (>=0.38)
Requires-Dist: numpy (>=1.12.0)
Requires-Dist: pinyin (>=0.4.0)
Requires-Dist: regex (>=2017.2.8)
Requires-Dist: scikit-learn (>=0.18.1)
Requires-Dist: scipy (>=0.18.1)
Requires-Dist: tensorflow (>=1.0.1)
